profile_url_local/__init__.py
profile_url_local/constants_url_profile_local.py
profile_url_local/profile_url_local.py
profile_url_local/url.py
profile_url_local-0.0.9.dist-info/METADATA
profile_url_local-0.0.9.dist-info/WHEEL
profile_url_local-0.0.9.dist-info/top_level.txt
profile_url_local-0.0.9.dist-info/RECORD
